LICENSE
LICENSES
dbd/__init__.py
dbd/cli/dbdcli.py
dbd/config/dbd_profile.py
dbd/config/dbd_project.py
dbd/db/db_column.py
dbd/db/db_schema.py
dbd/db/db_table.py
dbd/executors/model_executor.py
dbd/generator/generator_templates/column.j2
dbd/generator/generator_templates/macros.j2
dbd/generator/generator_templates/schema.j2
dbd/generator/generator_templates/table.j2
dbd/generator/jinja_generator_env.py
dbd/log/dbd_exception.py
dbd/log/dbd_logger.py
dbd/resources/template/dbd.profile
dbd/resources/template/dbd.project
dbd/resources/template/model/area.csv
dbd/resources/template/model/population.csv
dbd/resources/template/model/state.csv
dbd/tasks/data_task.py
dbd/tasks/db_table_task.py
dbd/tasks/ddl_task.py
dbd/tasks/elt_task.py
dbd/tasks/task.py
dbd/utils/io_utils.py
dbd/utils/jinja_utils.py
dbd/utils/profiling_utils.py
dbd/utils/sql_parser.py
dbd/utils/text_utils.py
dbd-0.8.9.dist-info/entry_points.txt
dbd-0.8.9.dist-info/LICENSE
dbd-0.8.9.dist-info/WHEEL
dbd-0.8.9.dist-info/METADATA
dbd-0.8.9.dist-info/RECORD
