Metadata-Version: 2.1
Name: dbd
Version: 0.8.9
Summary: dbd is a data loading and transformation tool that enables data analysts and engineers to load and transform data in SQL databases.
Home-page: https://github.com/zsvoboda/dbd/blob/master/README.md
License: BSD-3-Clause
Keywords: metadata,postgresql,database
Author: zsvoboda
Author-email: zsvoboda@gmail.com
Requires-Python: >=3.7.1,<3.11
Classifier: Development Status :: 4 - Beta
Classifier: Environment :: Console
Classifier: License :: OSI Approved :: BSD License
Classifier: Programming Language :: Python :: 3
Classifier: Programming Language :: Python :: 3.10
Classifier: Programming Language :: Python :: 3.8
Classifier: Programming Language :: Python :: 3.9
Classifier: Topic :: Database
Classifier: Topic :: Software Development
Classifier: Typing :: Typed
Requires-Dist: PyMySQL (>=1.0.2,<2.0.0)
Requires-Dist: cerberus (>=1.3.4,<2.0.0)
Requires-Dist: click (>=8.0.3,<9.0.0)
Requires-Dist: fsspec (==2022.1.0)
Requires-Dist: google-cloud-bigquery-storage (>=2.10.1,<3.0.0)
Requires-Dist: google-cloud-storage (>=2.1.0,<3.0.0)
Requires-Dist: greenlet (>=1.1.2,<2.0.0)
Requires-Dist: jinja2 (>=3.0.3,<4.0.0)
Requires-Dist: kaggle (>=1.5.12,<2.0.0)
Requires-Dist: networkx (>=2.6.3,<3.0.0)
Requires-Dist: openpyxl (>=3.0.9,<4.0.0)
Requires-Dist: pandas (>=1.3.5,<2.0.0)
Requires-Dist: pandas-gbq (>=0.17.0,<0.18.0)
Requires-Dist: psycopg2-binary (>=2.9.3,<3.0.0)
Requires-Dist: pyarrow (>=6.0.1,<7.0.0)
Requires-Dist: pyyaml (>=6.0,<7.0)
Requires-Dist: requests (>=2.27.1,<3.0.0)
Requires-Dist: s3fs (==2022.1.0)
Requires-Dist: snowflake-connector-python (>=2.7.4,<3.0.0)
Requires-Dist: snowflake-sqlalchemy (>=1.3.3,<2.0.0)
Requires-Dist: sql-metadata (>=2.3.0,<3.0.0)
Requires-Dist: sqlalchemy (>=1.4.25,<2.0.0)
Requires-Dist: sqlalchemy-bigquery (>=1.3.0,<2.0.0)
Requires-Dist: sqlalchemy-redshift (>=0.8.9,<0.9.0)
Requires-Dist: sqlparse (>=0.4.2,<0.5.0)
Project-URL: Documentation, https://github.com/zsvoboda/dbd/blob/master/README.md
Project-URL: Repository, https://github.com/zsvoboda/dbd
